parsuite/__init__.py
parsuite/decorators.py
parsuite/helpers.py
parsuite/abstractions/__init__.py
parsuite/abstractions/misc/__init__.py
parsuite/abstractions/misc/nmap.py
parsuite/abstractions/xml/__init__.py
parsuite/abstractions/xml/burp.py
parsuite/abstractions/xml/masscan.py
parsuite/abstractions/xml/nessus.py
parsuite/abstractions/xml/nmap.py
parsuite/abstractions/xml/validators.py
parsuite/abstractions/xml/generic/__init__.py
parsuite/abstractions/xml/generic/exceptions.py
parsuite/abstractions/xml/generic/network_host.py
parsuite/core/__init__.py
parsuite/core/argument.py
parsuite/core/suffix_printer.py
parsuite/modules/__init__.py
parsuite/modules/apex_domains/__init__.py
parsuite/modules/apex_domains/apex_domains.py
parsuite/modules/bloodhound_property_manager/__init__.py
parsuite/modules/bloodhound_property_manager/bloodhound_property_manager.py
parsuite/modules/bloodhound_property_manager_neo4j/__init__.py
parsuite/modules/bloodhound_property_manager_neo4j/bloodhound_property_manager_neo4j.py
parsuite/modules/burp_info_extractor/__init__.py
parsuite/modules/burp_info_extractor/burp_info_extractor.py
parsuite/modules/burp_items_to_authmatrix/__init__.py
parsuite/modules/burp_items_to_authmatrix/burp_items_to_authmatrix.py
parsuite/modules/burp_to_authmatrix/__init__.py
parsuite/modules/burp_to_authmatrix/burp_to_authmatrix.py
parsuite/modules/crt_sh/__init__.py
parsuite/modules/crt_sh/crt_sh.py
parsuite/modules/csharp_hexarray_parser/__init__.py
parsuite/modules/csharp_hexarray_parser/csharp_hexarray_parser.py
parsuite/modules/encoder/__init__.py
parsuite/modules/encoder/encoder.py
parsuite/modules/hash_linker/__init__.py
parsuite/modules/hash_linker/hash_linker.py
parsuite/modules/hc_kerberoast_dumper/__init__.py
parsuite/modules/hc_kerberoast_dumper/hc_kerberoast_dumper.py
parsuite/modules/ip_expander/__init__.py
parsuite/modules/ip_expander/ip_expander.py
parsuite/modules/ip_sorter/__init__.py
parsuite/modules/ip_sorter/ip_sorter.py
parsuite-0.0.0.dist-info/LICENSE
parsuite-0.0.0.dist-info/METADATA
parsuite-0.0.0.dist-info/WHEEL
parsuite-0.0.0.dist-info/top_level.txt
parsuite-0.0.0.dist-info/RECORD
