Metadata-Version: 2.1
Name: parsuite
Version: 0.0.0
Summary: A framework to parse common things.
Home-page: https://github.com/arch4ngel/parsuite
Author: Justin Angel
Author-email: justin@arch4ngel.ninja
License: UNKNOWN
Platform: UNKNOWN
Classifier: Programming Language :: Python :: 3
Classifier: License :: OSI Approved :: MIT License
Classifier: Operating System :: POSIX :: Linux
Requires-Python: >=3.9
Requires-Dist: IPython
Requires-Dist: colored (==1.3.93)
Requires-Dist: django
Requires-Dist: jsbeautifier
Requires-Dist: lxml
Requires-Dist: neo4j (>=4.2.1)
Requires-Dist: nessrest
Requires-Dist: netaddr (==0.7.19)
Requires-Dist: netinfo
Requires-Dist: publicsuffix2
Requires-Dist: python-slugify
Requires-Dist: tabulate
Requires-Dist: termcolor
